{
  "fold_metrics": [
    {
      "accuracy": 0.7777777777777778,
      "balanced_accuracy": 0.75,
      "precision": 0.6666666666666666,
      "recall": 0.6666666666666666,
      "f1": 0.6666666666666666,
      "roc_auc": 0.7222222222222222,
      "fold": 1
    },
    {
      "accuracy": 0.8888888888888888,
      "balanced_accuracy": 0.9166666666666667,
      "precision": 0.75,
      "recall": 1.0,
      "f1": 0.8571428571428571,
      "roc_auc": 0.888888888888889,
      "fold": 2
    },
    {
      "accuracy": 0.8888888888888888,
      "balanced_accuracy": 0.9166666666666667,
      "precision": 0.75,
      "recall": 1.0,
      "f1": 0.8571428571428571,
      "roc_auc": 1.0,
      "fold": 3
    },
    {
      "accuracy": 0.6666666666666666,
      "balanced_accuracy": 0.5833333333333334,
      "precision": 0.5,
      "recall": 0.3333333333333333,
      "f1": 0.4,
      "roc_auc": 0.5555555555555556,
      "fold": 4
    },
    {
      "accuracy": 0.6666666666666666,
      "balanced_accuracy": 0.5,
      "precision": 0.0,
      "recall": 0.0,
      "f1": 0.0,
      "roc_auc": 0.888888888888889,
      "fold": 5
    },
    {
      "accuracy": 0.7777777777777778,
      "balanced_accuracy": 0.75,
      "precision": 0.6666666666666666,
      "recall": 0.6666666666666666,
      "f1": 0.6666666666666666,
      "roc_auc": 0.7777777777777779,
      "fold": 6
    },
    {
      "accuracy": 0.875,
      "balanced_accuracy": 0.9,
      "precision": 0.75,
      "recall": 1.0,
      "f1": 0.8571428571428571,
      "roc_auc": 1.0,
      "fold": 7
    },
    {
      "accuracy": 0.625,
      "balanced_accuracy": 0.5666666666666667,
      "precision": 0.5,
      "recall": 0.3333333333333333,
      "f1": 0.4,
      "roc_auc": 0.7333333333333333,
      "fold": 8
    },
    {
      "accuracy": 0.75,
      "balanced_accuracy": 0.7333333333333334,
      "precision": 0.6666666666666666,
      "recall": 0.6666666666666666,
      "f1": 0.6666666666666666,
      "roc_auc": 0.6666666666666666,
      "fold": 9
    },
    {
      "accuracy": 0.875,
      "balanced_accuracy": 0.8333333333333333,
      "precision": 1.0,
      "recall": 0.6666666666666666,
      "f1": 0.8,
      "roc_auc": 0.8,
      "fold": 10
    }
  ],
  "accuracy_mean": 0.7791666666666666,
  "accuracy_std": 0.09611472375997752,
  "balanced_accuracy_mean": 0.745,
  "balanced_accuracy_std": 0.14453949863849214,
  "precision_mean": 0.625,
  "precision_std": 0.24790791301072526,
  "recall_mean": 0.6333333333333334,
  "recall_std": 0.3144660377352201,
  "f1_mean": 0.6171428571428571,
  "f1_std": 0.2624427375184737,
  "roc_auc_mean": 0.8033333333333335,
  "roc_auc_std": 0.13572393913499928
}